rosinenpicker/__init__.py
rosinenpicker/start.py
rosinenpicker/data/__init__.py
rosinenpicker/data/database.py
rosinenpicker/data/pydantic_models.py
rosinenpicker/processing/__init__.py
rosinenpicker/processing/exporter.py
rosinenpicker/processing/patterns.py
rosinenpicker/processing/processors.py
rosinenpicker/utils/__init__.py
rosinenpicker/utils/utils.py
rosinenpicker-0.1.17.dist-info/METADATA
rosinenpicker-0.1.17.dist-info/WHEEL
rosinenpicker-0.1.17.dist-info/entry_points.txt
rosinenpicker-0.1.17.dist-info/licenses/LICENSE
rosinenpicker-0.1.17.dist-info/RECORD
