Metadata-Version: 2.1
Name: rosinenpicker
Version: 0.1.17
Summary: A package for picking the juciest text morsels out of a pile of documents.
Project-URL: Homepage, https://github.com/joheli/rosinenpicker
Project-URL: Issues, https://github.com/joheli/rosinenpicker/issues
Author-email: Johannes Elias <joheli@gmx.net>
License-File: LICENSE
Classifier: Development Status :: 2 - Pre-Alpha
Classifier: Environment :: Console
Classifier: License :: OSI Approved :: MIT License
Classifier: Operating System :: OS Independent
Classifier: Programming Language :: Python :: 3
Requires-Python: >=3.11
Requires-Dist: pandas>=2.2.0
Requires-Dist: pdfminer-six>=20231228
Requires-Dist: pydantic>=2.6.1
Requires-Dist: python-docx>=1.1.0
Requires-Dist: pyyaml>=6.0.1
Requires-Dist: sqlalchemy>=2.0.27
